{
  "project_info": {
    "project_number": "279966051757",
    "project_id": "admin-panel-c91d7",
    "storage_bucket": "admin-panel-c91d7.appspot.com"
  },
  "client": [
    {
      "client_info": {
        "mobilesdk_app_id": "1:279966051757:android:a6a6f461ae09d1e4564524",
        "android_client_info": {
          "package_name": "uz.creator.adminpanel"
        }
      },
      "oauth_client": [
        {
          "client_id": "279966051757-67gbu2snvtpgjtphts0ec4lesbct1uhb.apps.googleusercontent.com",
          "client_type": 3
        }
      ],
      "api_key": [
        {
          "current_key": "AIzaSyAjQkARe2cWGqvKUr2mlHHB6EW1-Rlc1E8"
        }
      ],
      "services": {
        "appinvite_service": {
          "other_platform_oauth_client": [
            {
              "client_id": "279966051757-67gbu2snvtpgjtphts0ec4lesbct1uhb.apps.googleusercontent.com",
              "client_type": 3
            }
          ]
        }
      }
    }
  ],
  "configuration_version": "1"
}